[
    {
        "name": "Amused"
    },
    {
        "name": "Angry"
    },
    {
        "name": "Anxious"
    },
    {
        "name": "Bored"
    },
    {
        "name": "Calm"
    },
    {
        "name": "Confused"
    },
    {
        "name": "Content"
    },
    {
        "name": "Disappointed"
    },
    {
        "name": "Embarrassed"
    },
    {
        "name": "Envious"
    },
    {
        "name": "Excited"
    },
    {
        "name": "Frustrated"
    },
    {
        "name": "Grateful"
    },
    {
        "name": "Guilt"
    },
    {
        "name": "Happy"
    },
    {
        "name": "Hopeful"
    },
    {
        "name": "Joyful"
    },
    {
        "name": "Lonely"
    },
    {
        "name": "Loved"
    },
    {
        "name": "Proud"
    },
    {
        "name": "Relieved"
    },
    {
        "name": "Sad"
    },
    {
        "name": "Scared"
    },
    {
        "name": "Shy"
    },
    {
        "name": "Surprised"
    }
]